{
  "countryCode": "KP",
  "countryName": "Korea, Democratic People's Republic of",
  "holidays": [
    {
      "date": "2026-01-01",
      "localizedNames": {
        "de": "Neujahr",
        "en": "New Year's Day",
        "es": "Año Nuevo",
        "fr": "Jour de l'An",
        "ja": "元日",
        "ko": "신정",
        "pt": "Ano Novo",
        "zh": "元旦"
      },
      "type": "PUBLIC"
    },
    {
      "date": "2026-02-08",
      "localizedNames": {
        "de": "Founding Day of the Korean People's Army",
        "en": "Founding Day of the Korean People's Army",
        "es": "Founding Day of the Korean People's Army",
        "fr": "Founding Day of the Korean People's Army",
        "ja": "Founding Day of the Korean People's Army",
        "ko": "Founding Day of the Korean People's Army",
        "pt": "Founding Day of the Korean People's Army",
        "zh": "Founding Day of the Korean People's Army"
      },
      "type": "PUBLIC"
    },
    {
      "date": "2026-02-16",
      "localizedNames": {
        "de": "Day of the Shining Star",
        "en": "Day of the Shining Star",
        "es": "Day of the Shining Star",
        "fr": "Day of the Shining Star",
        "ja": "Day of the Shining Star",
        "ko": "Day of the Shining Star",
        "pt": "Day of the Shining Star",
        "zh": "Day of the Shining Star"
      },
      "type": "PUBLIC"
    },
    {
      "date": "2026-02-17",
      "localizedNames": {
        "de": "Day of the Shining Star; Korean New Year",
        "en": "Day of the Shining Star; Korean New Year",
        "es": "Day of the Shining Star; Korean New Year",
        "fr": "Day of the Shining Star; Korean New Year",
        "ja": "Day of the Shining Star; Korean New Year",
        "ko": "Day of the Shining Star; Korean New Year",
        "pt": "Day of the Shining Star; Korean New Year",
        "zh": "Day of the Shining Star; Korean New Year"
      },
      "type": "PUBLIC"
    },
    {
      "date": "2026-04-15",
      "localizedNames": {
        "de": "Day of the Sun",
        "en": "Day of the Sun",
        "es": "Day of the Sun",
        "fr": "Day of the Sun",
        "ja": "Day of the Sun",
        "ko": "Day of the Sun",
        "pt": "Day of the Sun",
        "zh": "Day of the Sun"
      },
      "type": "PUBLIC"
    },
    {
      "date": "2026-04-25",
      "localizedNames": {
        "de": "Founding Day of the Korean People's Revolutionary Army",
        "en": "Founding Day of the Korean People's Revolutionary Army",
        "es": "Founding Day of the Korean People's Revolutionary Army",
        "fr": "Founding Day of the Korean People's Revolutionary Army",
        "ja": "Founding Day of the Korean People's Revolutionary Army",
        "ko": "Founding Day of the Korean People's Revolutionary Army",
        "pt": "Founding Day of the Korean People's Revolutionary Army",
        "zh": "Founding Day of the Korean People's Revolutionary Army"
      },
      "type": "PUBLIC"
    },
    {
      "date": "2026-06-06",
      "localizedNames": {
        "de": "Foundation Day of the Korean Children's Union",
        "en": "Foundation Day of the Korean Children's Union",
        "es": "Foundation Day of the Korean Children's Union",
        "fr": "Foundation Day of the Korean Children's Union",
        "ja": "Foundation Day of the Korean Children's Union",
        "ko": "Foundation Day of the Korean Children's Union",
        "pt": "Foundation Day of the Korean Children's Union",
        "zh": "Foundation Day of the Korean Children's Union"
      },
      "type": "PUBLIC"
    },
    {
      "date": "2026-07-27",
      "localizedNames": {
        "de": "Day of Victory in the Great Fatherland Liberation War",
        "en": "Day of Victory in the Great Fatherland Liberation War",
        "es": "Day of Victory in the Great Fatherland Liberation War",
        "fr": "Day of Victory in the Great Fatherland Liberation War",
        "ja": "Day of Victory in the Great Fatherland Liberation War",
        "ko": "Day of Victory in the Great Fatherland Liberation War",
        "pt": "Day of Victory in the Great Fatherland Liberation War",
        "zh": "Day of Victory in the Great Fatherland Liberation War"
      },
      "type": "PUBLIC"
    },
    {
      "date": "2026-08-15",
      "localizedNames": {
        "de": "Tag der Befreiung",
        "en": "Liberation Day",
        "es": "Día de la Liberación",
        "fr": "Jour de la Libération",
        "ja": "解放記念日",
        "ko": "해방기념일",
        "pt": "Dia da Libertação",
        "zh": "解放日"
      },
      "type": "PUBLIC"
    },
    {
      "date": "2026-08-25",
      "localizedNames": {
        "de": "Day of Songun",
        "en": "Day of Songun",
        "es": "Day of Songun",
        "fr": "Day of Songun",
        "ja": "Day of Songun",
        "ko": "Day of Songun",
        "pt": "Day of Songun",
        "zh": "Day of Songun"
      },
      "type": "PUBLIC"
    },
    {
      "date": "2026-09-09",
      "localizedNames": {
        "de": "Founding Day of the DPRK",
        "en": "Founding Day of the DPRK",
        "es": "Founding Day of the DPRK",
        "fr": "Founding Day of the DPRK",
        "ja": "Founding Day of the DPRK",
        "ko": "Founding Day of the DPRK",
        "pt": "Founding Day of the DPRK",
        "zh": "Founding Day of the DPRK"
      },
      "type": "PUBLIC"
    },
    {
      "date": "2026-10-10",
      "localizedNames": {
        "de": "Foundation Day of the Workers' Party of Korea",
        "en": "Foundation Day of the Workers' Party of Korea",
        "es": "Foundation Day of the Workers' Party of Korea",
        "fr": "Foundation Day of the Workers' Party of Korea",
        "ja": "Foundation Day of the Workers' Party of Korea",
        "ko": "Foundation Day of the Workers' Party of Korea",
        "pt": "Foundation Day of the Workers' Party of Korea",
        "zh": "Foundation Day of the Workers' Party of Korea"
      },
      "type": "PUBLIC"
    },
    {
      "date": "2026-12-27",
      "localizedNames": {
        "de": "Socialist Constitution Day",
        "en": "Socialist Constitution Day",
        "es": "Socialist Constitution Day",
        "fr": "Socialist Constitution Day",
        "ja": "Socialist Constitution Day",
        "ko": "Socialist Constitution Day",
        "pt": "Socialist Constitution Day",
        "zh": "Socialist Constitution Day"
      },
      "type": "PUBLIC"
    },
    {
      "date": "2027-01-01",
      "localizedNames": {
        "de": "Neujahr",
        "en": "New Year's Day",
        "es": "Año Nuevo",
        "fr": "Jour de l'An",
        "ja": "元日",
        "ko": "신정",
        "pt": "Ano Novo",
        "zh": "元旦"
      },
      "type": "PUBLIC"
    },
    {
      "date": "2027-02-08",
      "localizedNames": {
        "de": "Founding Day of the Korean People's Army",
        "en": "Founding Day of the Korean People's Army",
        "es": "Founding Day of the Korean People's Army",
        "fr": "Founding Day of the Korean People's Army",
        "ja": "Founding Day of the Korean People's Army",
        "ko": "Founding Day of the Korean People's Army",
        "pt": "Founding Day of the Korean People's Army",
        "zh": "Founding Day of the Korean People's Army"
      },
      "type": "PUBLIC"
    },
    {
      "date": "2027-02-16",
      "localizedNames": {
        "de": "Day of the Shining Star",
        "en": "Day of the Shining Star",
        "es": "Day of the Shining Star",
        "fr": "Day of the Shining Star",
        "ja": "Day of the Shining Star",
        "ko": "Day of the Shining Star",
        "pt": "Day of the Shining Star",
        "zh": "Day of the Shining Star"
      },
      "type": "PUBLIC"
    },
    {
      "date": "2027-02-17",
      "localizedNames": {
        "de": "Day of the Shining Star; Korean New Year",
        "en": "Day of the Shining Star; Korean New Year",
        "es": "Day of the Shining Star; Korean New Year",
        "fr": "Day of the Shining Star; Korean New Year",
        "ja": "Day of the Shining Star; Korean New Year",
        "ko": "Day of the Shining Star; Korean New Year",
        "pt": "Day of the Shining Star; Korean New Year",
        "zh": "Day of the Shining Star; Korean New Year"
      },
      "type": "PUBLIC"
    },
    {
      "date": "2027-04-15",
      "localizedNames": {
        "de": "Day of the Sun",
        "en": "Day of the Sun",
        "es": "Day of the Sun",
        "fr": "Day of the Sun",
        "ja": "Day of the Sun",
        "ko": "Day of the Sun",
        "pt": "Day of the Sun",
        "zh": "Day of the Sun"
      },
      "type": "PUBLIC"
    },
    {
      "date": "2027-04-25",
      "localizedNames": {
        "de": "Founding Day of the Korean People's Revolutionary Army",
        "en": "Founding Day of the Korean People's Revolutionary Army",
        "es": "Founding Day of the Korean People's Revolutionary Army",
        "fr": "Founding Day of the Korean People's Revolutionary Army",
        "ja": "Founding Day of the Korean People's Revolutionary Army",
        "ko": "Founding Day of the Korean People's Revolutionary Army",
        "pt": "Founding Day of the Korean People's Revolutionary Army",
        "zh": "Founding Day of the Korean People's Revolutionary Army"
      },
      "type": "PUBLIC"
    },
    {
      "date": "2027-06-06",
      "localizedNames": {
        "de": "Foundation Day of the Korean Children's Union",
        "en": "Foundation Day of the Korean Children's Union",
        "es": "Foundation Day of the Korean Children's Union",
        "fr": "Foundation Day of the Korean Children's Union",
        "ja": "Foundation Day of the Korean Children's Union",
        "ko": "Foundation Day of the Korean Children's Union",
        "pt": "Foundation Day of the Korean Children's Union",
        "zh": "Foundation Day of the Korean Children's Union"
      },
      "type": "PUBLIC"
    },
    {
      "date": "2027-07-27",
      "localizedNames": {
        "de": "Day of Victory in the Great Fatherland Liberation War",
        "en": "Day of Victory in the Great Fatherland Liberation War",
        "es": "Day of Victory in the Great Fatherland Liberation War",
        "fr": "Day of Victory in the Great Fatherland Liberation War",
        "ja": "Day of Victory in the Great Fatherland Liberation War",
        "ko": "Day of Victory in the Great Fatherland Liberation War",
        "pt": "Day of Victory in the Great Fatherland Liberation War",
        "zh": "Day of Victory in the Great Fatherland Liberation War"
      },
      "type": "PUBLIC"
    },
    {
      "date": "2027-08-15",
      "localizedNames": {
        "de": "Tag der Befreiung",
        "en": "Liberation Day",
        "es": "Día de la Liberación",
        "fr": "Jour de la Libération",
        "ja": "解放記念日",
        "ko": "해방기념일",
        "pt": "Dia da Libertação",
        "zh": "解放日"
      },
      "type": "PUBLIC"
    },
    {
      "date": "2027-08-25",
      "localizedNames": {
        "de": "Day of Songun",
        "en": "Day of Songun",
        "es": "Day of Songun",
        "fr": "Day of Songun",
        "ja": "Day of Songun",
        "ko": "Day of Songun",
        "pt": "Day of Songun",
        "zh": "Day of Songun"
      },
      "type": "PUBLIC"
    },
    {
      "date": "2027-09-09",
      "localizedNames": {
        "de": "Founding Day of the DPRK",
        "en": "Founding Day of the DPRK",
        "es": "Founding Day of the DPRK",
        "fr": "Founding Day of the DPRK",
        "ja": "Founding Day of the DPRK",
        "ko": "Founding Day of the DPRK",
        "pt": "Founding Day of the DPRK",
        "zh": "Founding Day of the DPRK"
      },
      "type": "PUBLIC"
    },
    {
      "date": "2027-10-10",
      "localizedNames": {
        "de": "Foundation Day of the Workers' Party of Korea",
        "en": "Foundation Day of the Workers' Party of Korea",
        "es": "Foundation Day of the Workers' Party of Korea",
        "fr": "Foundation Day of the Workers' Party of Korea",
        "ja": "Foundation Day of the Workers' Party of Korea",
        "ko": "Foundation Day of the Workers' Party of Korea",
        "pt": "Foundation Day of the Workers' Party of Korea",
        "zh": "Foundation Day of the Workers' Party of Korea"
      },
      "type": "PUBLIC"
    },
    {
      "date": "2027-12-27",
      "localizedNames": {
        "de": "Socialist Constitution Day",
        "en": "Socialist Constitution Day",
        "es": "Socialist Constitution Day",
        "fr": "Socialist Constitution Day",
        "ja": "Socialist Constitution Day",
        "ko": "Socialist Constitution Day",
        "pt": "Socialist Constitution Day",
        "zh": "Socialist Constitution Day"
      },
      "type": "PUBLIC"
    }
  ],
  "schemaVersion": 2,
  "timeZone": "Asia/Pyongyang",
  "years": [
    2026,
    2027
  ]
}